MANIFEST.in
README.rst
setup.py
version.txt
micral_harmonic_core/__init__.py
micral_harmonic_core/micral_harmonic_core.py
micral_harmonic_core/version.txt
micral_harmonic_core.egg-info/PKG-INFO
micral_harmonic_core.egg-info/SOURCES.txt
micral_harmonic_core.egg-info/dependency_links.txt
micral_harmonic_core.egg-info/not-zip-safe
micral_harmonic_core.egg-info/requires.txt
micral_harmonic_core.egg-info/top_level.txt